TermIO/KeyCodes.py
TermIO/__init__.py
TermIO/in/__init__.py
TermIO/out/__init__.py
in/__init__.py
out/__init__.py
TermIO-0.1.6.dist-info/LICENSE
TermIO-0.1.6.dist-info/METADATA
TermIO-0.1.6.dist-info/WHEEL
TermIO-0.1.6.dist-info/top_level.txt
TermIO-0.1.6.dist-info/RECORD
