Metadata-Version: 2.1
Name: TermIO
Version: 0.1.6
Summary: Simple terminal manipulator
Home-page: https://github.com/jakobst1n/TermIO-python-package
Author: jakobst1n
Author-email: jakob.stendahl@outlook.com
License: UNKNOWN
Platform: UNKNOWN
Classifier: Programming Language :: Python :: 3
Classifier: Operating System :: OS Independent
